bookserver/__init__.py
bookserver/__main__.py
bookserver/applogger.py
bookserver/config.py
bookserver/crud.py
bookserver/db.py
bookserver/internal/__init__.py
bookserver/internal/common_builder.py
bookserver/internal/feedback.py
bookserver/internal/scheduled_builder.py
bookserver/internal/toctree.rst
bookserver/internal/utils.py
bookserver/main.py
bookserver/models.py
bookserver/routers/__init__.py
bookserver/routers/assessment.py
bookserver/routers/auth.py
bookserver/routers/books.py
bookserver/routers/coach.py
bookserver/routers/discuss.py
bookserver/routers/rslogging.py
bookserver/routers/toctree.rst
bookserver/schemas.py
bookserver/session.py
bookserver/staticAssets/RAIcon.png
bookserver/staticAssets/books.js
bookserver/staticAssets/index.css
bookserver/staticAssets/main.css
bookserver/templates/auth/login.html
bookserver/templates/books/_base.html
bookserver/templates/books/footer.html
bookserver/templates/books/index.html
bookserver/toctree.rst
bookserver-1.5.1.dist-info/LICENSE.rst
bookserver-1.5.1.dist-info/METADATA
bookserver-1.5.1.dist-info/WHEEL
bookserver-1.5.1.dist-info/entry_points.txt
bookserver-1.5.1.dist-info/RECORD
