Metadata-Version: 2.1
Name: bookserver
Version: 1.5.1
Summary: A new Runestone Server Framework
License: MIT
Author: Brad Miller
Author-email: bonelake@mac.com
Requires-Python: >=3.9.0,<4.0.0
Classifier: License :: OSI Approved :: MIT License
Classifier: Programming Language :: Python :: 3
Classifier: Programming Language :: Python :: 3.9
Classifier: Programming Language :: Python :: 3.10
Classifier: Programming Language :: Python :: 3.11
Requires-Dist: Jinja2 (<3.1.0)
Requires-Dist: SQLAlchemy (>=1.0.0,<2.0.0)
Requires-Dist: aiofiles (>=0.8.0,<0.9.0)
Requires-Dist: aioredis (>=2.0.0,<3.0.0)
Requires-Dist: aiosqlite (>=0.17.0,<0.18.0)
Requires-Dist: alembic (>=1.0.0,<2.0.0)
Requires-Dist: async-timeout (>=3.0.0,<4.0.0)
Requires-Dist: asyncpg (>=0.24.0,<0.25.0)
Requires-Dist: bleach (>=4.0.0,<5.0.0)
Requires-Dist: celery[redis] (>=5.0.0,<6.0.0)
Requires-Dist: fastapi (>=0.87.0,<0.88.0)
Requires-Dist: fastapi-login (>=1.8.0,<2.0.0)
Requires-Dist: flake8 (>=6.0.0,<7.0.0)
Requires-Dist: gunicorn (>=20.0.0,<21.0.0) ; sys_platform != "win32"
Requires-Dist: multi-await (>=1.0.0,<2.0.0)
Requires-Dist: pydal (>=20210215.1)
Requires-Dist: pyflakes (>=3.0.1,<4.0.0)
Requires-Dist: pyhumps (>=3.0.0,<4.0.0)
Requires-Dist: python-dateutil (>=2.0.0,<3.0.0)
Requires-Dist: python-multipart (>=0.0.5,<0.0.6)
Requires-Dist: redis (>=4.0.0,<5.0.0)
Requires-Dist: runestone (>=6.0.0,<7.0.0)
Requires-Dist: uvicorn[standard] (>=0.17.0,<0.18.0)
Project-URL: Documentation, https://bookserver.readthedocs.io/en/latest/
